{
  "address": "0xe66baa0b612003af308d78f066bbdb9a5e00ff6c",
  "discovered_at": "2026-01-09T13:34:58.028288",
  "total_value_usd": 4285128.713588201,
  "eth_balance": 164.7820519393452,
  "eth_value_usd": 329564.1038786904,
  "token_holdings": {
    "USDT": {
      "balance": 3311378.812571,
      "value_usd": 3311378.812571
    },
    "USDC": {
      "balance": 502967.546022,
      "value_usd": 502967.546022
    },
    "WETH": {
      "balance": 0.19583050826929335,
      "value_usd": 391.6610165385867
    },
    "DAI": {
      "balance": 140826.59009997203,
      "value_usd": 140826.59009997203
    }
  },
  "category": "likely_individual",
  "risk_score": 65,
  "osint_categories": [
    "\ud83c\udd95_newcomers",
    "\ud83d\udca4_dormant_whales",
    "\ud83d\udc1f_easy_targets",
    "\ud83e\udd8a_cautious_holders",
    "\ud83d\udc8e_high_value",
    "\ud83c\udfaf_prime_targets"
  ],
  "priority_score": 75,
  "last_triage": "2026-01-14T15:44:52.546484Z"
}